mintrans/__init__.py
mintrans/async_mintrans.py
mintrans/mintrans.py
mintrans-1.1.0.dist-info/LICENSE
mintrans-1.1.0.dist-info/METADATA
mintrans-1.1.0.dist-info/WHEEL
mintrans-1.1.0.dist-info/top_level.txt
mintrans-1.1.0.dist-info/RECORD
