Metadata-Version: 2.1
Name: mintrans
Version: 1.1.0
Summary: Mintrans is a free API wrapper that utilizes Bing, DeepL, and Google Translate for translation purposes.
Home-page: https://github.com/DedInc/mintrans
Author: Maehdakvan
Author-email: visitanimation@google.com
Project-URL: Bug Tracker, https://github.com/DedInc/mintrans/issues
Classifier: Programming Language :: Python :: 3
Classifier: License :: OSI Approved :: MIT License
Classifier: Operating System :: OS Independent
Requires-Python: >=3.6
License-File: LICENSE
Requires-Dist: requests
Requires-Dist: aiohttp
Requires-Dist: asyncio
